{
  "src": {
    "autocompletes": "AutoCompletes",
    "barcodereaders": "BarcodeReaders",
    "checkboxlists": "CheckboxLists",
    "datetimepickers": "DateTimePickers",
    "datetimeranges": "DateTimeRanges",
    "dropdownlists": "DropdownLists",
    "dropdownwidgets": "DropdownWidgets",
    "editdialogs": "EditDialogs",
    "editorforms": "EditorForms",
    "groupboxs": "GroupBoxs",
    "inputnumbers": "InputNumbers",
    "listviews": "ListViews",
    "multi-selects": "MultiSelect",
    "popconfirms": "PopoverConfirms",
    "qrcodes": "QRCodes",
    "searchdialogs": "SearchDialogs",
    "swals": "SweetAlerts",
    "tables": "Table/Tables",
    "autorefresh": "Table/TablesAutoRefresh",
    "column": "Table/TablesColumn",
    "detail": "Table/TablesDetailRow",
    "dialog": "Table/TablesDialog",
    "edit": "Table/TablesEdit",
    "export": "Table/TablesExport",
    "filter": "Table/TablesFilter",
    "fix-column": "Table/TablesFixedColumn",
    "header": "Table/TablesFixedHeader",
    "footer": "Table/TablesFooter",
    "multi-header": "Table/TablesHeader",
    "pages": "Table/TablesPages",
    "row": "Table/TablesRow",
    "search": "Table/TablesSearch",
    "selection": "Table/TablesSelection",
    "toolbar": "Table/TablesToolbar",
    "wrap": "Table/TablesWrap"
  },
  "video": {
    "tables": "BV11y4y1e7Sr",
    "autorefresh": "BV1jA411H7NZ",
    "column": "BV1hp4y1B79r",
    "detail": "BV1jh41127U6",
    "dialog": "BV1Et4y1r7qr",
    "edit": "BV1Et4y1r7qr",
    "export": "BV1Et4y1r7qr",
    "filter": "BV1df4y1C7ud",
    "fix-column": "BV15o4y1f7eN",
    "header": "BV15o4y1f7eN",
    "footer": "BV15o4y1f7eN",
    "multi-header": "BV15o4y1f7eN",
    "pages": "BV1Et4y1r7qr",
    "row": "BV1jh41127U6",
    "search": "BV1df4y1C7ud",
    "selection": "BV1jh41127U6",
    "toolbar": "BV1Et4y1r7qr",
    "wrap": "BV1ry4y127Fm"
  }
}
